py_tree_sitter_epics/__init__.py
py_tree_sitter_epics/epicsdb.py
py_tree_sitter_epics-0.2.2.dist-info/METADATA
py_tree_sitter_epics-0.2.2.dist-info/WHEEL
py_tree_sitter_epics-0.2.2.dist-info/RECORD
