Metadata-Version: 2.3
Name: py-tree-sitter-epics
Version: 0.2.2
Summary: Facilitate tree-sitter-epics parsing in python
Author: Alexis Gaget
Author-email: alexis.gaget@cea.fr
Requires-Python: >=3.10,<4.0
Classifier: Programming Language :: Python :: 3
Classifier: Programming Language :: Python :: 3.10
Classifier: Programming Language :: Python :: 3.11
Classifier: Programming Language :: Python :: 3.12
Classifier: Programming Language :: Python :: 3.13
Requires-Dist: pytest (>=8.4.2,<9.0.0)
Requires-Dist: tree-sitter (>=0.25.2,<0.26.0)
Requires-Dist: tree-sitter-epics-db (>=0.2.0,<0.3.0)
